karyoplot/__init__.py
karyoplot/confparser.py
karyoplot/entities.py
karyoplot/main.py
karyoplot/version.py
karyoplot-0.0.3.dist-info/LICENSE
karyoplot-0.0.3.dist-info/METADATA
karyoplot-0.0.3.dist-info/WHEEL
karyoplot-0.0.3.dist-info/entry_points.txt
karyoplot-0.0.3.dist-info/top_level.txt
karyoplot-0.0.3.dist-info/RECORD
