Metadata-Version: 2.1
Name: karyoplot
Version: 0.0.3
Summary: karyoplot: annotations along the genome
Home-page: https://forgemia.inra.fr/bioger/karyoplot
Author: Nicolas Lapalu
Author-email: nicolas.lapalu@inrae.fr
Classifier: Intended Audience :: Science/Research
Classifier: License :: OSI Approved :: GNU General Public License v3 (GPLv3)
Classifier: Operating System :: POSIX
Classifier: Operating System :: Unix
Classifier: Topic :: Scientific/Engineering
Classifier: Topic :: Scientific/Engineering :: Bio-Informatics
Classifier: Programming Language :: Python :: 3.7
Classifier: Programming Language :: Python :: 3.8
Classifier: Programming Language :: Python :: 3.9
Classifier: Programming Language :: Python :: 3.10
License-File: LICENSE
Requires-Dist: numpy
Requires-Dist: pysam
Requires-Dist: matplotlib
Requires-Dist: pandas
